ldap2html/__init__.py
ldap2html/html/__init__.py
ldap2html/html/model.py
ldap2html/html2ldif/__init__.py
ldap2html/html2ldif/config.py
ldap2html/html2ldif/convert.py
ldap2html/html2ldif/main.py
ldap2html/ldap/__init__.py
ldap2html/ldap/model.py
ldap2html/ldap/utils.py
ldap2html/ldap2html/__init__.py
ldap2html/ldap2html/config.py
ldap2html/ldap2html/convert.py
ldap2html/ldap2html/main.py
ldap2html-0.4.0.dist-info/entry_points.txt
ldap2html-0.4.0.dist-info/LICENSE
ldap2html-0.4.0.dist-info/WHEEL
ldap2html-0.4.0.dist-info/METADATA
ldap2html-0.4.0.dist-info/RECORD
